MANIFEST.in
README.rst
setup.py
holdouts_generator/__init__.py
holdouts_generator/__version__.py
holdouts_generator/balanced_random_holdouts.py
holdouts_generator/chromosomal_holdout.py
holdouts_generator/holdouts_generator.py
holdouts_generator/random_holdout.py
holdouts_generator/store_results.py
holdouts_generator/work_in_progress.py
holdouts_generator.egg-info/PKG-INFO
holdouts_generator.egg-info/SOURCES.txt
holdouts_generator.egg-info/dependency_links.txt
holdouts_generator.egg-info/requires.txt
holdouts_generator.egg-info/top_level.txt
holdouts_generator/utils/__init__.py
holdouts_generator/utils/cache.py
holdouts_generator/utils/hash.py
holdouts_generator/utils/holdouts_description.py
holdouts_generator/utils/json.py
holdouts_generator/utils/metrics.py
holdouts_generator/utils/paths.py
holdouts_generator/utils/various.py