Metadata-Version: 2.1
Name: holdouts-generator
Version: 0.0.52
Summary: Simple python package to generate and cache both random and chromosomal holdouts with arbitrary depth.
Home-page: https://github.com/LucaCappelletti94/holdouts_generator
Author: Luca Cappelletti
Author-email: cappelletti.luca94@gmail.com
License: MIT
Platform: UNKNOWN
Classifier: Development Status :: 3 - Alpha
Classifier: License :: OSI Approved :: MIT License
Classifier: Programming Language :: Python :: 3
Provides-Extra: test
